coop_mcp_demo/__init__.py
coop_mcp_demo-0.1.0.dist-info/METADATA
coop_mcp_demo-0.1.0.dist-info/WHEEL
coop_mcp_demo-0.1.0.dist-info/entry_points.txt
coop_mcp_demo-0.1.0.dist-info/RECORD
