Metadata-Version: 2.4
Name: coop-mcp-demo
Version: 0.1.0
Summary: Add your description here
Requires-Python: >=3.11.9
Requires-Dist: mcp[cli]>=1.10.1
